MANIFEST.in
README
README.markdown
setup.py
feincms_jobs/__init__.py
feincms_jobs/admin.py
feincms_jobs/content.py
feincms_jobs/models.py
feincms_jobs/tests.py
feincms_jobs/views.py
feincms_jobs.egg-info/PKG-INFO
feincms_jobs.egg-info/SOURCES.txt
feincms_jobs.egg-info/dependency_links.txt
feincms_jobs.egg-info/requires.txt
feincms_jobs.egg-info/top_level.txt
feincms_jobs/templates/admin/feincms_jobs/job/change_form.html
feincms_jobs/templates/feincms_jobs/job_detail.html