Metadata-Version: 1.0
Name: feincms-jobs
Version: 0.1
Summary: A FeinCMS Plugin for job listings.
Home-page: http://github.com/incuna/feincms-jobs
Author: Incuna Ltd
Author-email: dev@incuna.com
License: UNKNOWN
Platform: UNKNOWN
